pytezos_core/__init__.py
pytezos_core/encoding.py
pytezos_core/hash.py
pytezos_core/jupyter.py
pytezos_core/key.py
pytezos_core/py.typed
pytezos_core-1.0.0rc1.dist-info/LICENSE.md
pytezos_core-1.0.0rc1.dist-info/WHEEL
pytezos_core-1.0.0rc1.dist-info/METADATA
pytezos_core-1.0.0rc1.dist-info/RECORD
